paradict/__init__.py
paradict/__main__.py
paradict/box/__init__.py
paradict/configfile/__init__.py
paradict/const/__init__.py
paradict/datatype/__init__.py
paradict/deserializer/__init__.py
paradict/deserializer/buffered_bin_stream.py
paradict/deserializer/buffered_text_stream.py
paradict/deserializer/decoder.py
paradict/deserializer/scanner.py
paradict/deserializer/unpacker.py
paradict/document/__init__.py
paradict/errors/__init__.py
paradict/filedoc/__init__.py
paradict/io_bin/__init__.py
paradict/io_text/__init__.py
paradict/kv/__init__.py
paradict/misc/__init__.py
paradict/queue/__init__.py
paradict/queue/bin_queue.py
paradict/queue/txt_queue.py
paradict/serializer/__init__.py
paradict/serializer/encoder.py
paradict/serializer/packer.py
paradict/spec/bin_paradict_spec.md
paradict/spec/txt_paradict_spec.md
paradict/tags/__init__.py
paradict/tags/mappings.py
paradict/tags/misc.py
paradict/typeref/__init__.py
paradict/validator/__init__.py
paradict/xtypes/__init__.py
tests/__init__.py
tests/__main__.py
tests/test_imports.py
tests/box/__init__.py
tests/box/test_box.py
tests/configfile/__init__.py
tests/configfile/test_configfile.py
tests/deserializer/__init__.py
tests/deserializer/test_decoder.py
tests/deserializer/test_funcs.py
tests/deserializer/test_unpacker.py
tests/document/__init__.py
tests/document/test_document.py
tests/filedoc/__init__.py
tests/filedoc/test_file_doc.py
tests/kv/__init__.py
tests/kv/test_kv.py
tests/misc/__init__.py
tests/misc/test_misc.py
tests/queue/__init__.py
tests/queue/test_bin_queue.py
tests/queue/test_txt_queue.py
tests/serializer/__init__.py
tests/serializer/test_encoder.py
tests/serializer/test_funcs.py
tests/serializer/test_packer.py
tests/streaming/__init__.py
tests/streaming/test_bin_streaming.py
tests/streaming/test_txt_streaming.py
tests/validator/__init__.py
tests/validator/test_validator.py
paradict-0.0.15.dist-info/LICENSE
paradict-0.0.15.dist-info/METADATA
paradict-0.0.15.dist-info/WHEEL
paradict-0.0.15.dist-info/entry_points.txt
paradict-0.0.15.dist-info/top_level.txt
paradict-0.0.15.dist-info/RECORD
